bd_time/__init__.py
bd_time/cleaners.py
bd_time/extractor.py
bd_time/my_time.py
bd_time/titles.py
bd_time-0.0.1.dist-info/LICENSE.txt
bd_time-0.0.1.dist-info/METADATA
bd_time-0.0.1.dist-info/WHEEL
bd_time-0.0.1.dist-info/top_level.txt
bd_time-0.0.1.dist-info/RECORD
