Metadata-Version: 2.1
Name: bd-time
Version: 0.0.1
Summary: bode's private time model.
Home-page: https://github.com/bode135/pydamo
Author: bode135
Author-email: 2248270222@qq.com
License: UNKNOWN
Platform: UNKNOWN
Classifier: Programming Language :: Python :: 3
Classifier: License :: OSI Approved :: MIT License
Classifier: Operating System :: OS Independent
Requires-Python: >=3.6
